fwup/__init__.py
fwup/core.py
fwup/dfu.py
fwup/errors.py
fwup/fx3.py
fwup/lpc43xx.py
fwup/micronucleus.py
fwup_utils/__init__.py
fwup_utils/fwup_util.py
pyfwup-0.5.3.dist-info/licenses/LICENSE
pyfwup-0.5.3.dist-info/METADATA
pyfwup-0.5.3.dist-info/WHEEL
pyfwup-0.5.3.dist-info/entry_points.txt
pyfwup-0.5.3.dist-info/top_level.txt
pyfwup-0.5.3.dist-info/RECORD
